geocachingapi/__init__.py
geocachingapi/const.py
geocachingapi/exceptions.py
geocachingapi/geocachingapi.py
geocachingapi/models.py
geocachingapi/py.typed
geocachingapi/utils.py
geocachingapi-0.2.3.dist-info/LICENSE
geocachingapi-0.2.3.dist-info/METADATA
geocachingapi-0.2.3.dist-info/WHEEL
geocachingapi-0.2.3.dist-info/top_level.txt
geocachingapi-0.2.3.dist-info/RECORD
